{
  "id": "glass-frosted",
  "scaffoldId": "dashboard",
  "label": "Glass Frosted",
  "description": "Modern SaaS analytics dashboard with frosted surfaces and layered depth.",
  "keywords": [
    "analytics",
    "dashboard",
    "saas",
    "glass",
    "metrics",
    "workspace",
    "modern"
  ],
  "fontPairings": [
    {
      "heading": "Space Grotesk",
      "body": "Inter"
    }
  ],
  "signatureMotif": "frosted panels, layered cards, and subtle glowing metrics",
  "colorMode": "dark",
  "promptHints": [
    "Keep information density high, but use translucent depth to separate zones cleanly.",
    "This should feel operational, polished, and product-grade rather than brochure-like."
  ],
  "themeTokens": {
    "background": "oklch(0.16 0.015 250)",
    "foreground": "oklch(0.94 0.006 250)",
    "card": "oklch(0.21 0.015 250)",
    "primary": "oklch(0.7 0.18 280)",
    "primaryForeground": "oklch(0.12 0 0)",
    "secondary": "oklch(0.24 0.015 250)",
    "muted": "oklch(0.22 0.01 250)",
    "accent": "oklch(0.62 0.14 220)",
    "border": "oklch(0.3 0.01 250)",
    "ring": "oklch(0.7 0.18 280)",
    "radius": "1rem"
  },
  "sourceTemplateIds": [
    "ecommerce-blazity-enterprise-ecommerce-starter",
    "authentication-clerk-authentication-starter",
    "admin-dashboard-modernize-next-js-admin-dashboard-template",
    "authentication-next-js-saas-starter"
  ],
  "default": true
}
